Points_cli/Points_cli.py
Points_cli/__init__.py
Points_cli-0.1.2.data/scripts/Points_cli.py
Points_cli-0.1.2.dist-info/LICENSE
Points_cli-0.1.2.dist-info/METADATA
Points_cli-0.1.2.dist-info/WHEEL
Points_cli-0.1.2.dist-info/entry_points.txt
Points_cli-0.1.2.dist-info/top_level.txt
Points_cli-0.1.2.dist-info/RECORD
