Metadata-Version: 2.1
Name: Points-cli
Version: 0.1.2
Summary: Plots and measures angles and distances between points in 3-Dimensions
Home-page: https://github.com/Ridhiwan/Points-cli
Author: Ridhiwan Ramadhan Mseya
Author-email: ridhiwanmseya@gmail.com
License: MIT
Platform: UNKNOWN
Classifier: Programming Language :: Python :: 3
Classifier: License :: OSI Approved :: MIT License
Classifier: Operating System :: POSIX :: Linux
Requires-Python: >=3.6
Requires-Dist: numpy
Requires-Dist: matplotlib
Requires-Dist: tqdm
